centaur/_/pyvmps/main.py
centaur/_/pyvmps/cfg/config.py
centaur/_/pyvmps/cfg/constants.py
centaur/_/pyvmps/cfg/versioned_model.py
centaur/_/pyvmps/client/constants.py
centaur/_/pyvmps/client/exceptions.py
centaur/_/pyvmps/client/model_controller.py
centaur/_/pyvmps/client/pyvmp.py
centaur/_/pyvmps/client/usr_payload_parser.py
centaur/_/pyvmps/client/utils.py
centaur/_/pyvmps/client/pyvmp_models/_tf_helper.py
centaur/_/pyvmps/client/pyvmp_models/python.py
centaur/_/pyvmps/client/pyvmp_models/python_whl.py
centaur/_/pyvmps/client/pyvmp_models/tf1.py
centaur/_/pyvmps/client/pyvmp_models/tf2.py
centaur/_/pyvmps/communicator/adapter.py
centaur/_/pyvmps/communicator/exceptions.py
centaur/_/pyvmps/communicator/socket_base.py
centaur/_/pyvmps/communicator/socket_base_test.py
centaur/_/pyvmps/communicator/utils.py
centaur/_/pyvmps/communicator/utils_test.py
centaur/_/pyvmps/error_handling/constants.py
centaur/_/pyvmps/error_handling/errors.py
centaur/_/pyvmps/logger/get_logger.py
centaur/_/pyvmps/logger/_/config.py
centaur/_/pyvmps/logger/_/escape_codes.py
centaur/_/pyvmps/logger/_/filters.py
centaur/_/pyvmps/logger/_/formatters.py
centaur/_/pyvmps/models/base_model.py
centaur/_/pyvmps/models/centaur_model.py
centaur/_/pyvmps/models/exceptions.py
centaur/_/pyvmps/models/python/constants.py
centaur/_/pyvmps/models/python/model.py
centaur/_/pyvmps/models/python/utils.py
centaur/_/pyvmps/models/tf/constants.py
centaur/_/pyvmps/models/tf/types.py
centaur/_/pyvmps/models/tf/utils.py
centaur/_/pyvmps/models/tf/tf1/model.py
centaur/_/pyvmps/models/tf/tf1/payload_utils.py
centaur/_/pyvmps/models/tf/tf2/model.py
centaur/_/pyvmps/models/tf/tf2/payload_utils.py
centaur/_/pyvmps/tracking/constants.py
centaur/_/pyvmps/tracking/tracker.py
centaur/_/pyvmps/utils/common.py
centaur/constants/__init__.py
sap_computer_vision/DISCLAIMER
sap_computer_vision/LICENSE
sap_computer_vision/RELEASE_INFO
sap_computer_vision/__init__.py
sap_computer_vision/ai_core_content_spec.py
sap_computer_vision_package-1.1.7.dist-info/LICENSE
sap_computer_vision_package-1.1.7.dist-info/METADATA
sap_computer_vision_package-1.1.7.dist-info/WHEEL
sap_computer_vision_package-1.1.7.dist-info/top_level.txt
sap_computer_vision_package-1.1.7.dist-info/RECORD
