Metadata-Version: 2.1
Name: sap-computer-vision-package
Version: 1.1.7
Summary: SAP Computer Vision Package
Home-page: https://www.sap.com/
Author: SAP SE
License: SAP DEVELOPER LICENSE AGREEMENT
Download-URL: https://pypi.python.org/pypi/sap-computer-vision-package
Keywords: SAP Computer Vision,SAP Computer Vision Package,SAP AI Core
Platform: UNKNOWN
Classifier: Development Status :: 5 - Production/Stable
Classifier: Intended Audience :: Developers
Classifier: Intended Audience :: End Users/Desktop
Classifier: Intended Audience :: Financial and Insurance Industry
Classifier: Intended Audience :: Healthcare Industry
Classifier: Intended Audience :: Information Technology
Classifier: Intended Audience :: Legal Industry
Classifier: Intended Audience :: Manufacturing
Classifier: Intended Audience :: Science/Research
Classifier: License :: Other/Proprietary License
Classifier: Operating System :: MacOS :: MacOS X
Classifier: Operating System :: POSIX :: Linux
Classifier: Topic :: Scientific/Engineering
Classifier: Topic :: Scientific/Engineering :: Artificial Intelligence
Classifier: Topic :: Scientific/Engineering :: Image Recognition
Classifier: Topic :: Software Development :: Libraries
Classifier: Topic :: Software Development :: Libraries :: Python Modules
Classifier: Programming Language :: Python
Classifier: Programming Language :: Python :: 3
Requires-Python: >=3.6
Requires-Dist: setuptools (==58.0.4)
Requires-Dist: numpy (~=1.21.0)
Requires-Dist: scipy (~=1.7.0)
Requires-Dist: torch (~=1.10.0)
Requires-Dist: torchvision (~=0.11.0)
Requires-Dist: timm (~=0.5.4)
Requires-Dist: Pillow (~=9.0.0)
Requires-Dist: click (~=8.0.0)
Requires-Dist: fvcore
Requires-Dist: Jinja2
Requires-Dist: opencv-python
Requires-Dist: slugify
Requires-Dist: termcolor
Requires-Dist: tabulate
Requires-Dist: environs (==9.0.0)
Requires-Dist: ujson (==4.0.0)
Requires-Dist: psutil (==5.7.2)
Requires-Dist: shortuuid (==1.0.1)
Requires-Dist: requests-toolbelt (==0.9.1)
